{"cameraMode":{"drawMode":0,"name":"Shaded","section":"Shading Mode"},"sceneLighting":false,"audioPlay":false,"sceneViewState":{"m_AlwaysRefresh":false,"showFog":true,"showSkybox":false,"showFlares":true,"showImageEffects":true,"showParticleSystems":true,"showVisualEffectGraphs":true,"m_FxEnabled":true},"in2DMode":false,"pivot":{"x":5.4373884201049809,"y":2.8697943687438967,"z":-0.5523389577865601},"rotation":{"x":-0.24914006888866425,"y":0.5285679697990418,"z":-0.16576243937015534,"w":-0.794413149356842},"size":1.874983787536621,"orthographic":false}